OptionGreekPricing/BinomialTrees.py
OptionGreekPricing/BlackScholes.py
OptionGreekPricing/Greeks.py
OptionGreekPricing/MonteCarlo.py
OptionGreekPricing/PutCall.py
OptionGreekPricing/__init__.py
option_greek_pricing-1.0.3.dist-info/LICENSE.txt
option_greek_pricing-1.0.3.dist-info/METADATA
option_greek_pricing-1.0.3.dist-info/WHEEL
option_greek_pricing-1.0.3.dist-info/top_level.txt
option_greek_pricing-1.0.3.dist-info/RECORD
