Metadata-Version: 2.1
Name: option-greek-pricing
Version: 1.0.3
Summary: A package written in Python with equations to calculate option Prices and Greeks.
Home-page: https://github.com/mh2rashi/OptionGreeksPricing
Author: Hamza Rashid
Author-email: hamza022697@gmail.com
License: UNKNOWN
Keywords: finance,options,greeks
Platform: UNKNOWN
Classifier: Development Status :: 3 - Alpha
Classifier: Intended Audience :: Developers
Classifier: Intended Audience :: Science/Research
Classifier: Intended Audience :: Financial and Insurance Industry
Classifier: License :: OSI Approved :: MIT License
Classifier: Natural Language :: English
Classifier: Operating System :: OS Independent
Classifier: Programming Language :: Python
Classifier: Programming Language :: Python :: 3
Classifier: Programming Language :: Python :: 3.8
Classifier: Topic :: Database
Classifier: Topic :: Education
Classifier: Topic :: Office/Business
Requires-Python: >=3.8
Requires-Dist: numpy
Requires-Dist: scipy
